html_dom_visualize/__init__.py
html_dom_visualize/main.py
html_dom_visualize/visualizer.py
html_dom_visualize-0.2.7.dist-info/LICENSE
html_dom_visualize-0.2.7.dist-info/METADATA
html_dom_visualize-0.2.7.dist-info/WHEEL
html_dom_visualize-0.2.7.dist-info/entry_points.txt
html_dom_visualize-0.2.7.dist-info/RECORD
