Metadata-Version: 2.1
Name: html-dom-visualize
Version: 0.2.7
Summary: A simple HTML to Tree Diagram library that outputs HTML DOM as image for visualization.
Home-page: https://github.com/lokwkin/html-dom-visualize
License: MIT
Keywords: dom,html,visualization,tree,diagram,html-dom-visualize
Author: lokwkin
Author-email: lokwkin@gmail.com
Requires-Python: >=3.8,<4.0
Classifier: License :: OSI Approved :: MIT License
Classifier: Programming Language :: Python :: 3
Classifier: Programming Language :: Python :: 3.8
Classifier: Programming Language :: Python :: 3.9
Classifier: Programming Language :: Python :: 3.10
Classifier: Programming Language :: Python :: 3.11
Classifier: Programming Language :: Python :: 3.12
Requires-Dist: beautifulsoup4 (>=4.12.3,<5.0.0)
Requires-Dist: kaleido (==0.2.1)
Requires-Dist: plotly (==5.22.0)
Requires-Dist: pytest (>=8.3.1,<9.0.0)
Requires-Dist: pytest-mock (>=3.14.0,<4.0.0)
Requires-Dist: requests (>=2.32.3,<3.0.0)
Project-URL: Repository, https://github.com/lokwkin/html-dom-visualize
